aio_ownet/__init__.py
aio_ownet/connection.py
aio_ownet/definitions.py
aio_ownet/exceptions.py
aio_ownet/proxy.py
aio_ownet/py.typed
aio_ownet/utils.py
aio_ownet-0.0.5.dist-info/METADATA
aio_ownet-0.0.5.dist-info/WHEEL
aio_ownet-0.0.5.dist-info/entry_points.txt
aio_ownet-0.0.5.dist-info/licenses/LICENSE
aio_ownet-0.0.5.dist-info/RECORD
