Metadata-Version: 2.4
Name: aio-ownet
Version: 0.0.5
Summary: Async OWFS (owserver) client
License: MIT
License-File: LICENSE
Keywords: owfs,owserver
Author: epenet
Requires-Python: >=3.11,<4.0
Classifier: Intended Audience :: Developers
Classifier: Intended Audience :: System Administrators
Classifier: License :: OSI Approved :: MIT License
Classifier: Operating System :: OS Independent
Classifier: Programming Language :: Python :: 3
Classifier: Programming Language :: Python :: 3.11
Classifier: Programming Language :: Python :: 3.12
Classifier: Programming Language :: Python :: 3.13
Classifier: Programming Language :: Python :: 3.14
Classifier: Topic :: Home Automation
Provides-Extra: cli
Requires-Dist: click (>=8.0.1) ; extra == "cli"
Project-URL: Changelog, https://github.com/hacf-fr/aio-ownet/releases
Project-URL: Documentation, https://aio-ownet.readthedocs.io
Project-URL: Homepage, https://github.com/hacf-fr/aio-ownet
Project-URL: Repository, https://github.com/hacf-fr/aio-ownet
